snowday_predictor/__init__.py
snowday_predictor/predictor.py
snowdaypredictor_API-1.0.1.dist-info/LICENSE
snowdaypredictor_API-1.0.1.dist-info/METADATA
snowdaypredictor_API-1.0.1.dist-info/WHEEL
snowdaypredictor_API-1.0.1.dist-info/top_level.txt
snowdaypredictor_API-1.0.1.dist-info/RECORD
